{
  "updated_at": "2026-03-04 12:55",
  "date": "2026-03-04",
  "indices": [
    {
      "name": "KOSPI",
      "value": 5093.54,
      "change": -12.06,
      "diff": -698.37,
      "ascn": 13,
      "down": 911,
      "tr_amt": 62882735.0
    },
    {
      "name": "KOSDAQ",
      "value": 978.44,
      "change": -14.0,
      "diff": -159.26,
      "ascn": 25,
      "down": 1708,
      "tr_amt": 16587060.0
    },
    {
      "name": "KOSPI200",
      "value": 5415.85,
      "change": -12.05,
      "diff": -742.21,
      "ascn": 0,
      "down": 99,
      "tr_amt": 51899908.0
    }
  ],
  "sectors": [
    {
      "iscd": "1028",
      "name": "에너지",
      "mkt_type": "KOSPI",
      "value": 1685.76,
      "change": -14.29,
      "tr_amt": 3.559828,
      "history": []
    },
    {
      "iscd": "1029",
      "name": "소재",
      "mkt_type": "KOSPI",
      "value": 2255.4,
      "change": -13.51,
      "tr_amt": 0.840779,
      "history": []
    },
    {
      "iscd": "1030",
      "name": "산업재",
      "mkt_type": "KOSPI",
      "value": 5371.3,
      "change": -15.24,
      "tr_amt": 0.42001,
      "history": []
    },
    {
      "iscd": "1031",
      "name": "경기소비재",
      "mkt_type": "KOSPI",
      "value": 626.95,
      "change": -9.97,
      "tr_amt": 0.019353,
      "history": []
    },
    {
      "iscd": "1032",
      "name": "필수소비재",
      "mkt_type": "KOSPI",
      "value": 1101.49,
      "change": -9.32,
      "tr_amt": 0.008979,
      "history": []
    },
    {
      "iscd": "1033",
      "name": "건강관리",
      "mkt_type": "KOSPI",
      "value": 838.97,
      "change": -12.77,
      "tr_amt": 0.865553,
      "history": []
    },
    {
      "iscd": "1035",
      "name": "IT",
      "mkt_type": "KOSPI",
      "value": 5826.3,
      "change": -11.9,
      "tr_amt": 51.615831,
      "history": []
    },
    {
      "iscd": "1036",
      "name": "통신서비스",
      "mkt_type": "KOSPI",
      "value": 5529.24,
      "change": -11.75,
      "tr_amt": 41.950347,
      "history": []
    },
    {
      "iscd": "0003",
      "name": "대형주",
      "mkt_type": "KOSPI",
      "value": 3877.61,
      "change": -12.76,
      "tr_amt": 5.011414,
      "history": []
    },
    {
      "iscd": "0004",
      "name": "중형주",
      "mkt_type": "KOSPI",
      "value": 2510.98,
      "change": -10.0,
      "tr_amt": 3.557434,
      "history": []
    },
    {
      "iscd": "0005",
      "name": "소형주",
      "mkt_type": "KOSPI",
      "value": 4442.19,
      "change": -7.69,
      "tr_amt": 0.409427,
      "history": []
    },
    {
      "iscd": "2007",
      "name": "건설",
      "mkt_type": "KOSDAQ",
      "value": 5826.3,
      "change": -11.9,
      "tr_amt": 51.615831,
      "history": []
    },
    {
      "iscd": "2008",
      "name": "유통",
      "mkt_type": "KOSDAQ",
      "value": 5529.24,
      "change": -11.75,
      "tr_amt": 41.950347,
      "history": []
    },
    {
      "iscd": "2009",
      "name": "운송",
      "mkt_type": "KOSDAQ",
      "value": 619.08,
      "change": -14.61,
      "tr_amt": 0.974767,
      "history": []
    },
    {
      "iscd": "2010",
      "name": "금융",
      "mkt_type": "KOSDAQ",
      "value": 1319.63,
      "change": -15.56,
      "tr_amt": 4.087087,
      "history": []
    },
    {
      "iscd": "2011",
      "name": "오락문화",
      "mkt_type": "KOSDAQ",
      "value": 1333.76,
      "change": -15.49,
      "tr_amt": 0.976116,
      "history": []
    },
    {
      "iscd": "2012",
      "name": "통신방송",
      "mkt_type": "KOSDAQ",
      "value": 1575.63,
      "change": -14.06,
      "tr_amt": 3.327427,
      "history": []
    },
    {
      "iscd": "2013",
      "name": "인터넷",
      "mkt_type": "KOSDAQ",
      "value": 7542.62,
      "change": -11.8,
      "tr_amt": 28.722709,
      "history": []
    },
    {
      "iscd": "2014",
      "name": "디지털컨텐츠",
      "mkt_type": "KOSDAQ",
      "value": 1514.44,
      "change": -10.74,
      "tr_amt": 2.592788,
      "history": []
    },
    {
      "iscd": "2015",
      "name": "소프트웨어",
      "mkt_type": "KOSDAQ",
      "value": 1237.82,
      "change": -8.83,
      "tr_amt": 1.107484,
      "history": []
    },
    {
      "iscd": "2016",
      "name": "컴퓨터서비스",
      "mkt_type": "KOSDAQ",
      "value": 2579.15,
      "change": -14.21,
      "tr_amt": 3.945859,
      "history": []
    },
    {
      "iscd": "2017",
      "name": "통신장비",
      "mkt_type": "KOSDAQ",
      "value": 1228.36,
      "change": -12.8,
      "tr_amt": 7.360812,
      "history": []
    },
    {
      "iscd": "2018",
      "name": "IT부품",
      "mkt_type": "KOSDAQ",
      "value": 2183.94,
      "change": -12.59,
      "tr_amt": 0.804848,
      "history": []
    },
    {
      "iscd": "2019",
      "name": "반도체",
      "mkt_type": "KOSDAQ",
      "value": 5164.43,
      "change": -10.95,
      "tr_amt": 6.67417,
      "history": []
    },
    {
      "iscd": "2021",
      "name": "의료정밀기기",
      "mkt_type": "KOSDAQ",
      "value": 10801.29,
      "change": -12.29,
      "tr_amt": 42.130125,
      "history": []
    },
    {
      "iscd": "2022",
      "name": "음식료담배",
      "mkt_type": "KOSDAQ",
      "value": 2109.79,
      "change": -12.75,
      "tr_amt": 3.521809,
      "history": []
    }
  ],
  "stocks": [],
  "top_traders": {
    "foreign_buy": [],
    "foreign_sell": [],
    "inst_buy": [],
    "inst_sell": []
  },
  "market_supply": {
    "foreign_net": 0,
    "inst_net": 0,
    "indiv_net": 0
  },
  "phase_stats": {
    "golden": 0,
    "p2": 0,
    "p1": 0,
    "p3": 0,
    "new_high": 0
  },
  "summary_lines": [
    "KOSPI -12.06% (5,094)",
    "KOSDAQ -14.00% (978)",
    "외국인 +0만 / 기관 +0만 / 개인 +0만"
  ]
}